gymnasium_robotics/__init__.py
gymnasium_robotics/core.py
gymnasium_robotics/envs/__init__.py
gymnasium_robotics/envs/robot_env.py
gymnasium_robotics/envs/adroit_hand/__init__.py
gymnasium_robotics/envs/adroit_hand/adroit_door.py
gymnasium_robotics/envs/adroit_hand/adroit_hammer.py
gymnasium_robotics/envs/adroit_hand/adroit_pen.py
gymnasium_robotics/envs/adroit_hand/adroit_relocate.py
gymnasium_robotics/envs/assets/LICENSE.md
gymnasium_robotics/envs/assets/adroit_hand/adroit_assets.xml
gymnasium_robotics/envs/assets/adroit_hand/adroit_door.xml
gymnasium_robotics/envs/assets/adroit_hand/adroit_hammer.xml
gymnasium_robotics/envs/assets/adroit_hand/adroit_model.xml
gymnasium_robotics/envs/assets/adroit_hand/adroit_pen.xml
gymnasium_robotics/envs/assets/adroit_hand/adroit_relocate.xml
gymnasium_robotics/envs/assets/adroit_hand/resources/meshes/F1.stl
gymnasium_robotics/envs/assets/adroit_hand/resources/meshes/F2.stl
gymnasium_robotics/envs/assets/adroit_hand/resources/meshes/F3.stl
gymnasium_robotics/envs/assets/adroit_hand/resources/meshes/TH1_z.stl
gymnasium_robotics/envs/assets/adroit_hand/resources/meshes/TH2_z.stl
gymnasium_robotics/envs/assets/adroit_hand/resources/meshes/TH3_z.stl
gymnasium_robotics/envs/assets/adroit_hand/resources/meshes/arm_base.stl
gymnasium_robotics/envs/assets/adroit_hand/resources/meshes/arm_trunk.stl
gymnasium_robotics/envs/assets/adroit_hand/resources/meshes/arm_trunk_asmbly.stl
gymnasium_robotics/envs/assets/adroit_hand/resources/meshes/distal_ellipsoid.stl
gymnasium_robotics/envs/assets/adroit_hand/resources/meshes/elbow_flex.stl
gymnasium_robotics/envs/assets/adroit_hand/resources/meshes/elbow_rotate_motor.stl
gymnasium_robotics/envs/assets/adroit_hand/resources/meshes/elbow_rotate_muscle.stl
gymnasium_robotics/envs/assets/adroit_hand/resources/meshes/forearm_Cy_PlateAsmbly(muscle_cone).stl
gymnasium_robotics/envs/assets/adroit_hand/resources/meshes/forearm_Cy_PlateAsmbly.stl
gymnasium_robotics-1.4.0.dist-info/licenses/LICENSE
gymnasium_robotics-1.4.0.dist-info/METADATA
gymnasium_robotics-1.4.0.dist-info/WHEEL
gymnasium_robotics-1.4.0.dist-info/top_level.txt
gymnasium_robotics-1.4.0.dist-info/RECORD
