Metadata-Version: 2.4
Name: gymnasium-robotics
Version: 1.4.0
Summary: RL Robotics environments with Gymnasium Support.
Author-email: Farama Foundation <contact@farama.org>
License: MIT License
Project-URL: Homepage, https://farama.org
Project-URL: Repository, https://github.com/Farama-Foundation/Gymnasium-Robotics
Project-URL: Documentation, https://robotics.farama.org
Project-URL: Bug Report, https://github.com/Farama-Foundation/Gymnasium-Robotics/issues
Keywords: Reinforcement Learning,Gymnasium,RL,AI,Robotics
Classifier: Development Status :: 5 - Production/Stable
Classifier: License :: OSI Approved :: MIT License
Classifier: Programming Language :: Python :: 3
Classifier: Programming Language :: Python :: 3.10
Classifier: Programming Language :: Python :: 3.11
Classifier: Programming Language :: Python :: 3.12
Classifier: Programming Language :: Python :: 3.13
Classifier: Intended Audience :: Science/Research
Classifier: Topic :: Scientific/Engineering :: Artificial Intelligence
Requires-Python: >=3.10
License-File: LICENSE
Requires-Dist: mujoco>=2.2.0
Requires-Dist: numpy>=1.21.0
Requires-Dist: gymnasium>=1.2.0
Requires-Dist: PettingZoo>=1.23.0
Requires-Dist: Jinja2>=3.0.3
Requires-Dist: imageio
Requires-Dist: setuptools
Requires-Dist: packaging
Provides-Extra: testing
Requires-Dist: pytest==7.0.1; extra == "testing"
Requires-Dist: mujoco_py_cython3; extra == "testing"
Requires-Dist: PettingZoo>=1.23.0; extra == "testing"
Requires-Dist: Jinja2>=3.0.3; extra == "testing"
Provides-Extra: mujoco-py
Requires-Dist: mujoco_py_cython3; extra == "mujoco-py"
Provides-Extra: mujoco-py-original
Requires-Dist: mujoco_py<2.2,>=2.1; extra == "mujoco-py-original"
Requires-Dist: cython<3; extra == "mujoco-py-original"
Dynamic: license-file
